<?xml version="1.0" encoding="ISO-8859-1"?>
<item>
  <id>S-21</id>
  <date>2006-01-01</date>
  <category>05-01-02</category>
  <position>1</position>
  <icon>
    <deutsch>s-21.small.png</deutsch>
    <english>s-21.small.png</english>
    <français>s-21.small.png</français>
  </icon>
  <image>
    <deutsch>s-21.png</deutsch>
    <english>s-21.png</english>
    <français>s-21.png</français>
  </image>
  <name>
    <deutsch>S-21</deutsch>
    <english>S-21</english>
    <français>S-21</français>
  </name>
  <headline>
    <deutsch>Schwimmschalter Edelstahl</deutsch>
    <english>Float type switch made of special steel</english>
    <français>Interrupteur à flotteur en acier inox</français>
  </headline>
  <description>
    <deutsch>Einfache kostenguenstige Fuellstandsmessung mit ueberzeugendem Preis / Leistungsverhaeltnis
				Schwimmer aus Edelstahl (1.4571)
				Spezialkabel aus: Silikon und FEP (Teflon)
				Alle Schaltertypen als Einzelschalter, als Schalterkombination in Haenge- oder Stabausfuehrung
				Alle Schwimmschalter erhalten Sie in allen Groessen auch quecksilberfrei</deutsch>
    <english>Simple, cost-efficient level measuring with a convincing price / performance ratio
				Float made of special steel (1.4571)
				Special cable made of : silicone and  FEP (Teflon)
				All float type switches as single switch, as switch combination in suspended and bar type
				All float type switches are available in any size also mercury-free</english>
    <français>Mesure de niveau simple à un prix avantageux d´un rapport prix/performance convaincant
				Flotteur des matériaux acier inox (1.4571)
				Câble spécial en: silicone et FEP (téflon)
				Tous les types d´interrupteurs individuels comme combinaison d´interrupteurs du type suspendu ou baguette
				Tous les types d´interrupteurs sont livrables dans toutes les dimensions, également sans mercure</français>
  </description>
  <datasheet>
    <deutsch>
      <name>Datenblatt</name>
      <path>05/05-01-02-E-edelstahl_teflon_schwimmschalter.pdf</path>
    </deutsch>
    <english>
      <name>Datasheet</name>
      <path>05/05-01-02-E-edelstahl_teflon_schwimmschalter.pdf</path>
    </english>
    <français>
      <name>Fiche de données</name>
      <path>05/05-01-02-F-edelstahl_teflon_schwimmschalter.pdf</path>
    </français>
  </datasheet>
</item>
